QuantDataCollector/__init__.py
QuantDataCollector/data_collector.py
QuantDataCollector/Global/__init__.py
QuantDataCollector/Global/settings.py
QuantDataCollector/Utils/__init__.py
QuantDataCollector/Utils/file_utils.py
QuantDataCollector/Utils/mysql_utils.py
QuantDataCollector/Utils/utils.py
quantdatacollector-2.0.15.dist-info/LICENSE
quantdatacollector-2.0.15.dist-info/METADATA
quantdatacollector-2.0.15.dist-info/WHEEL
quantdatacollector-2.0.15.dist-info/top_level.txt
quantdatacollector-2.0.15.dist-info/RECORD
