Metadata-Version: 2.1
Name: QuantDataCollector
Version: 2.0.15
Summary: 为量化项目提供稳定且统一的数据接口
Home-page: https://github.com/QuantitativeInvestment/QuantDataCollector
Author: TX
Author-email: hanerzamora@gmail.com
License: MIT
License-File: LICENSE
Requires-Dist: datetime
Requires-Dist: baostock
Requires-Dist: pandas
Requires-Dist: pymysql
Requires-Dist: psycopg2
Requires-Dist: dbutils
